Workbook
Name FixedTotal: 'Fixed costs'!$B$37+VodafoneTotal
Name MonthEnd: EOMONTH(MonthStart,0)+1
Name MonthStart: DATE(YEAR(Overview!$C$5),MONTH(Overview!$C$5),1)
Name VodafoneTotal: SUMIFS('Vodafone bills'!$B$7:$B$126,'Vodafone bills'!$A$7:$A$126,">="&MonthStart,'Vodafone bills'!$A$7:$A$126,"<"&MonthEnd)

Sheet Overview
B2: Your money, day by day
B3: Track income and everyday spending. Keep recurring bills in Fixed costs.
B5: Month to review | C5: 46296
B6: Opening balance (optional) | C6: 0
B9: Income this month | C9: =SUMIFS('Daily entries'!$C$7:$C$2006,'Daily entries'!$A$7:$A$2006,">="&MonthStart,'Daily entries'!$A$7:$A$2006,"<"&MonthEnd) -> 0
B11: Everyday spending | C11: =SUMIFS('Daily entries'!$D$7:$D$2006,'Daily entries'!$A$7:$A$2006,">="&MonthStart,'Daily entries'!$A$7:$A$2006,"<"&MonthEnd) -> 0
B13: Monthly bills incl. Vodafone | C13: =FixedTotal -> 30617
B15: Remaining after fixed budget | C15: =C6+C9-C11-C13 -> -30617
B18: This is a budget balance, not your actual bank balance. The monthly bills budget is deducted, whether paid yet or not. Vodafone is excluded until its amount is entered. Do not enter the same bills again in Daily entries.
B23: Daily fixed-cost reserve | C23: =FixedTotal/DAY(EOMONTH(MonthStart,0)) -> 987.64516
B25: Your fixed expenses are assumed to be monthly: rent 19,500 Kč, internet 447 Kč, credit 10,670 Kč. Edit them in Fixed costs. Enter each Vodafone bill in Vodafone bills. Blue cells are editable.
E26: Start in Daily entries: enter a date, income or spending, and a short note. Review Daily summary for totals by day. Change the month above to review past or future entries.
B30: Vodafone this month | C30: =VodafoneTotal -> 0
B31: Vodafone entry status | C31: =IF(COUNTIFS('Vodafone bills'!$A$7:$A$126,">="&MonthStart,'Vodafone bills'!$A$7:$A$126,"<"&MonthEnd,'Vodafone bills'!$B$7:$B$126,"<>")=0,"Amount needed","Included") -> Amount needed
B32: Vodafone amount is not provided yet. Enter the actual monthly bill on Vodafone bills (date + amount); it is added to that month only. Do not also enter it in Daily entries or Fixed costs.

Sheet Daily entries
A2: Daily entries
A3: Enter income or everyday spending in positive CZK amounts. Vodafone belongs on Vodafone bills. You can use several rows for one day. Fixed bills belong only in Fixed costs. Enter dates, not text.
A6: Date | B6: Category | C6: Income (CZK) | D6: Spending (CZK) | E6: Entry net (CZK) | F6: Note
E7: =IF(A7="","",N(C7)-N(D7))
E8: =IF(A8="","",N(C8)-N(D8))
E9: =IF(A9="","",N(C9)-N(D9))
E10: =IF(A10="","",N(C10)-N(D10))
E11: =IF(A11="","",N(C11)-N(D11))
E12: =IF(A12="","",N(C12)-N(D12))
E13: =IF(A13="","",N(C13)-N(D13))
E14: =IF(A14="","",N(C14)-N(D14))
E15: =IF(A15="","",N(C15)-N(D15))
E16: =IF(A16="","",N(C16)-N(D16))
E17: =IF(A17="","",N(C17)-N(D17))
E18: =IF(A18="","",N(C18)-N(D18))
... E2006: =IF(A2006="","",N(C2006)-N(D2006))

Sheet Fixed costs
A2: Monthly fixed costs
A3: Monthly amounts apply to every selected month. Change blue cells to update your budget. These are planned costs; payment status is not tracked.
A6: Expense | B6: Monthly amount (CZK) | C6: Notes
A7: Rent | B7: 19500 | C7: Assumed monthly
A8: Internet | B8: 447 | C8: Assumed monthly
A9: Credit | B9: 10670 | C9: Assumed monthly
A37: Total monthly fixed costs | B37: =SUM(B7:B35) -> 30617

Sheet Daily summary
A2: Daily summary
A3: Selected month from Overview. Fixed reserve spreads monthly bills evenly over calendar days; it is a planning amount, not a payment. Running budget starts from your opening balance.
A6: Date | B6: Income (CZK) | C6: Everyday spending (CZK) | D6: Cash flow before fixed | E6: Fixed reserve (CZK) | F6: After fixed reserve | G6: Running budget (CZK)
A7: =IF(1<=DAY(EOMONTH(MonthStart,0)),MonthStart+0,"") -> 46296 | B7: =IF($A7="","",SUMIFS('Daily entries'!$C$7:$C$2006,'Daily entries'!$A$7:$A$2006,">="&$A7,'Daily entries'!$A$7:$A$2006,"<"&$A7+1)) -> 0 | C7: =IF($A7="","",SUMIFS('Daily entries'!$D$7:$D$2006,'Daily entries'!$A$7:$A$2006,">="&$A7,'Daily entries'!$A$7:$A$2006,"<"&$A7+1)) -> 0 | D7: =IF(A7="","",B7-C7) -> 0 | E7: =IF(A7="","",FixedTotal/DAY(EOMONTH(MonthStart,0))) -> 987.64516 | F7: =IF(A7="","",D7-E7) -> -987.64516 | G7: =IF(A7="","",Overview!$C$6+SUM($F$7:F7)) -> -987.64516
A8: =IF(2<=DAY(EOMONTH(MonthStart,0)),MonthStart+1,"") -> 46297 | B8: =IF($A8="","",SUMIFS('Daily entries'!$C$7:$C$2006,'Daily entries'!$A$7:$A$2006,">="&$A8,'Daily entries'!$A$7:$A$2006,"<"&$A8+1)) -> 0 | C8: =IF($A8="","",SUMIFS('Daily entries'!$D$7:$D$2006,'Daily entries'!$A$7:$A$2006,">="&$A8,'Daily entries'!$A$7:$A$2006,"<"&$A8+1)) -> 0 | D8: =IF(A8="","",B8-C8) -> 0 | E8: =IF(A8="","",FixedTotal/DAY(EOMONTH(MonthStart,0))) -> 987.64516 | F8: =IF(A8="","",D8-E8) -> -987.64516 | G8: =IF(A8="","",Overview!$C$6+SUM($F$7:F8)) -> -1975.2903
A9: =IF(3<=DAY(EOMONTH(MonthStart,0)),MonthStart+2,"") -> 46298 | B9: =IF($A9="","",SUMIFS('Daily entries'!$C$7:$C$2006,'Daily entries'!$A$7:$A$2006,">="&$A9,'Daily entries'!$A$7:$A$2006,"<"&$A9+1)) -> 0 | C9: =IF($A9="","",SUMIFS('Daily entries'!$D$7:$D$2006,'Daily entries'!$A$7:$A$2006,">="&$A9,'Daily entries'!$A$7:$A$2006,"<"&$A9+1)) -> 0 | D9: =IF(A9="","",B9-C9) -> 0 | E9: =IF(A9="","",FixedTotal/DAY(EOMONTH(MonthStart,0))) -> 987.64516 | F9: =IF(A9="","",D9-E9) -> -987.64516 | G9: =IF(A9="","",Overview!$C$6+SUM($F$7:F9)) -> -2962.9355
A10: =IF(4<=DAY(EOMONTH(MonthStart,0)),MonthStart+3,"") -> 46299 | B10: =IF($A10="","",SUMIFS('Daily entries'!$C$7:$C$2006,'Daily entries'!$A$7:$A$2006,">="&$A10,'Daily entries'!$A$7:$A$2006,"<"&$A10+1)) -> 0 | C10: =IF($A10="","",SUMIFS('Daily entries'!$D$7:$D$2006,'Daily entries'!$A$7:$A$2006,">="&$A10,'Daily entries'!$A$7:$A$2006,"<"&$A10+1)) -> 0 | D10: =IF(A10="","",B10-C10) -> 0 | E10: =IF(A10="","",FixedTotal/DAY(EOMONTH(MonthStart,0))) -> 987.64516 | F10: =IF(A10="","",D10-E10) -> -987.64516 | G10: =IF(A10="","",Overview!$C$6+SUM($F$7:F10)) -> -3950.5806
A11: =IF(5<=DAY(EOMONTH(MonthStart,0)),MonthStart+4,"") -> 46300 | B11: =IF($A11="","",SUMIFS('Daily entries'!$C$7:$C$2006,'Daily entries'!$A$7:$A$2006,">="&$A11,'Daily entries'!$A$7:$A$2006,"<"&$A11+1)) -> 0 | C11: =IF($A11="","",SUMIFS('Daily entries'!$D$7:$D$2006,'Daily entries'!$A$7:$A$2006,">="&$A11,'Daily entries'!$A$7:$A$2006,"<"&$A11+1)) -> 0 | D11: =IF(A11="","",B11-C11) -> 0 | E11: =IF(A11="","",FixedTotal/DAY(EOMONTH(MonthStart,0))) -> 987.64516 | F11: =IF(A11="","",D11-E11) -> -987.64516 | G11: =IF(A11="","",Overview!$C$6+SUM($F$7:F11)) -> -4938.2258
A12: =IF(6<=DAY(EOMONTH(MonthStart,0)),MonthStart+5,"") -> 46301 | B12: =IF($A12="","",SUMIFS('Daily entries'!$C$7:$C$2006,'Daily entries'!$A$7:$A$2006,">="&$A12,'Daily entries'!$A$7:$A$2006,"<"&$A12+1)) -> 0 | C12: =IF($A12="","",SUMIFS('Daily entries'!$D$7:$D$2006,'Daily entries'!$A$7:$A$2006,">="&$A12,'Daily entries'!$A$7:$A$2006,"<"&$A12+1)) -> 0 | D12: =IF(A12="","",B12-C12) -> 0 | E12: =IF(A12="","",FixedTotal/DAY(EOMONTH(MonthStart,0))) -> 987.64516 | F12: =IF(A12="","",D12-E12) -> -987.64516 | G12: =IF(A12="","",Overview!$C$6+SUM($F$7:F12)) -> -5925.871
A13: =IF(7<=DAY(EOMONTH(MonthStart,0)),MonthStart+6,"") -> 46302 | B13: =IF($A13="","",SUMIFS('Daily entries'!$C$7:$C$2006,'Daily entries'!$A$7:$A$2006,">="&$A13,'Daily entries'!$A$7:$A$2006,"<"&$A13+1)) -> 0 | C13: =IF($A13="","",SUMIFS('Daily entries'!$D$7:$D$2006,'Daily entries'!$A$7:$A$2006,">="&$A13,'Daily entries'!$A$7:$A$2006,"<"&$A13+1)) -> 0 | D13: =IF(A13="","",B13-C13) -> 0 | E13: =IF(A13="","",FixedTotal/DAY(EOMONTH(MonthStart,0))) -> 987.64516 | F13: =IF(A13="","",D13-E13) -> -987.64516 | G13: =IF(A13="","",Overview!$C$6+SUM($F$7:F13)) -> -6913.5161
A14: =IF(8<=DAY(EOMONTH(MonthStart,0)),MonthStart+7,"") -> 46303 | B14: =IF($A14="","",SUMIFS('Daily entries'!$C$7:$C$2006,'Daily entries'!$A$7:$A$2006,">="&$A14,'Daily entries'!$A$7:$A$2006,"<"&$A14+1)) -> 0 | C14: =IF($A14="","",SUMIFS('Daily entries'!$D$7:$D$2006,'Daily entries'!$A$7:$A$2006,">="&$A14,'Daily entries'!$A$7:$A$2006,"<"&$A14+1)) -> 0 | D14: =IF(A14="","",B14-C14) -> 0 | E14: =IF(A14="","",FixedTotal/DAY(EOMONTH(MonthStart,0))) -> 987.64516 | F14: =IF(A14="","",D14-E14) -> -987.64516 | G14: =IF(A14="","",Overview!$C$6+SUM($F$7:F14)) -> -7901.1613
A15: =IF(9<=DAY(EOMONTH(MonthStart,0)),MonthStart+8,"") -> 46304 | B15: =IF($A15="","",SUMIFS('Daily entries'!$C$7:$C$2006,'Daily entries'!$A$7:$A$2006,">="&$A15,'Daily entries'!$A$7:$A$2006,"<"&$A15+1)) -> 0 | C15: =IF($A15="","",SUMIFS('Daily entries'!$D$7:$D$2006,'Daily entries'!$A$7:$A$2006,">="&$A15,'Daily entries'!$A$7:$A$2006,"<"&$A15+1)) -> 0 | D15: =IF(A15="","",B15-C15) -> 0 | E15: =IF(A15="","",FixedTotal/DAY(EOMONTH(MonthStart,0))) -> 987.64516 | F15: =IF(A15="","",D15-E15) -> -987.64516 | G15: =IF(A15="","",Overview!$C$6+SUM($F$7:F15)) -> -8888.8065
A16: =IF(10<=DAY(EOMONTH(MonthStart,0)),MonthStart+9,"") -> 46305 | B16: =IF($A16="","",SUMIFS('Daily entries'!$C$7:$C$2006,'Daily entries'!$A$7:$A$2006,">="&$A16,'Daily entries'!$A$7:$A$2006,"<"&$A16+1)) -> 0 | C16: =IF($A16="","",SUMIFS('Daily entries'!$D$7:$D$2006,'Daily entries'!$A$7:$A$2006,">="&$A16,'Daily entries'!$A$7:$A$2006,"<"&$A16+1)) -> 0 | D16: =IF(A16="","",B16-C16) -> 0 | E16: =IF(A16="","",FixedTotal/DAY(EOMONTH(MonthStart,0))) -> 987.64516 | F16: =IF(A16="","",D16-E16) -> -987.64516 | G16: =IF(A16="","",Overview!$C$6+SUM($F$7:F16)) -> -9876.4516
A17: =IF(11<=DAY(EOMONTH(MonthStart,0)),MonthStart+10,"") -> 46306 | B17: =IF($A17="","",SUMIFS('Daily entries'!$C$7:$C$2006,'Daily entries'!$A$7:$A$2006,">="&$A17,'Daily entries'!$A$7:$A$2006,"<"&$A17+1)) -> 0 | C17: =IF($A17="","",SUMIFS('Daily entries'!$D$7:$D$2006,'Daily entries'!$A$7:$A$2006,">="&$A17,'Daily entries'!$A$7:$A$2006,"<"&$A17+1)) -> 0 | D17: =IF(A17="","",B17-C17) -> 0 | E17: =IF(A17="","",FixedTotal/DAY(EOMONTH(MonthStart,0))) -> 987.64516 | F17: =IF(A17="","",D17-E17) -> -987.64516 | G17: =IF(A17="","",Overview!$C$6+SUM($F$7:F17)) -> -10864.097
A18: =IF(12<=DAY(EOMONTH(MonthStart,0)),MonthStart+11,"") -> 46307 | B18: =IF($A18="","",SUMIFS('Daily entries'!$C$7:$C$2006,'Daily entries'!$A$7:$A$2006,">="&$A18,'Daily entries'!$A$7:$A$2006,"<"&$A18+1)) -> 0 | C18: =IF($A18="","",SUMIFS('Daily entries'!$D$7:$D$2006,'Daily entries'!$A$7:$A$2006,">="&$A18,'Daily entries'!$A$7:$A$2006,"<"&$A18+1)) -> 0 | D18: =IF(A18="","",B18-C18) -> 0 | E18: =IF(A18="","",FixedTotal/DAY(EOMONTH(MonthStart,0))) -> 987.64516 | F18: =IF(A18="","",D18-E18) -> -987.64516 | G18: =IF(A18="","",Overview!$C$6+SUM($F$7:F18)) -> -11851.742
A19: =IF(13<=DAY(EOMONTH(MonthStart,0)),MonthStart+12,"") -> 46308 | B19: =IF($A19="","",SUMIFS('Daily entries'!$C$7:$C$2006,'Daily entries'!$A$7:$A$2006,">="&$A19,'Daily entries'!$A$7:$A$2006,"<"&$A19+1)) -> 0 | C19: =IF($A19="","",SUMIFS('Daily entries'!$D$7:$D$2006,'Daily entries'!$A$7:$A$2006,">="&$A19,'Daily entries'!$A$7:$A$2006,"<"&$A19+1)) -> 0 | D19: =IF(A19="","",B19-C19) -> 0 | E19: =IF(A19="","",FixedTotal/DAY(EOMONTH(MonthStart,0))) -> 987.64516 | F19: =IF(A19="","",D19-E19) -> -987.64516 | G19: =IF(A19="","",Overview!$C$6+SUM($F$7:F19)) -> -12839.387
A20: =IF(14<=DAY(EOMONTH(MonthStart,0)),MonthStart+13,"") -> 46309 | B20: =IF($A20="","",SUMIFS('Daily entries'!$C$7:$C$2006,'Daily entries'!$A$7:$A$2006,">="&$A20,'Daily entries'!$A$7:$A$2006,"<"&$A20+1)) -> 0 | C20: =IF($A20="","",SUMIFS('Daily entries'!$D$7:$D$2006,'Daily entries'!$A$7:$A$2006,">="&$A20,'Daily entries'!$A$7:$A$2006,"<"&$A20+1)) -> 0 | D20: =IF(A20="","",B20-C20) -> 0 | E20: =IF(A20="","",FixedTotal/DAY(EOMONTH(MonthStart,0))) -> 987.64516 | F20: =IF(A20="","",D20-E20) -> -987.64516 | G20: =IF(A20="","",Overview!$C$6+SUM($F$7:F20)) -> -13827.032
A21: =IF(15<=DAY(EOMONTH(MonthStart,0)),MonthStart+14,"") -> 46310 | B21: =IF($A21="","",SUMIFS('Daily entries'!$C$7:$C$2006,'Daily entries'!$A$7:$A$2006,">="&$A21,'Daily entries'!$A$7:$A$2006,"<"&$A21+1)) -> 0 | C21: =IF($A21="","",SUMIFS('Daily entries'!$D$7:$D$2006,'Daily entries'!$A$7:$A$2006,">="&$A21,'Daily entries'!$A$7:$A$2006,"<"&$A21+1)) -> 0 | D21: =IF(A21="","",B21-C21) -> 0 | E21: =IF(A21="","",FixedTotal/DAY(EOMONTH(MonthStart,0))) -> 987.64516 | F21: =IF(A21="","",D21-E21) -> -987.64516 | G21: =IF(A21="","",Overview!$C$6+SUM($F$7:F21)) -> -14814.677
A22: =IF(16<=DAY(EOMONTH(MonthStart,0)),MonthStart+15,"") -> 46311 | B22: =IF($A22="","",SUMIFS('Daily entries'!$C$7:$C$2006,'Daily entries'!$A$7:$A$2006,">="&$A22,'Daily entries'!$A$7:$A$2006,"<"&$A22+1)) -> 0 | C22: =IF($A22="","",SUMIFS('Daily entries'!$D$7:$D$2006,'Daily entries'!$A$7:$A$2006,">="&$A22,'Daily entries'!$A$7:$A$2006,"<"&$A22+1)) -> 0 | D22: =IF(A22="","",B22-C22) -> 0 | E22: =IF(A22="","",FixedTotal/DAY(EOMONTH(MonthStart,0))) -> 987.64516 | F22: =IF(A22="","",D22-E22) -> -987.64516 | G22: =IF(A22="","",Overview!$C$6+SUM($F$7:F22)) -> -15802.323
A23: =IF(17<=DAY(EOMONTH(MonthStart,0)),MonthStart+16,"") -> 46312 | B23: =IF($A23="","",SUMIFS('Daily entries'!$C$7:$C$2006,'Daily entries'!$A$7:$A$2006,">="&$A23,'Daily entries'!$A$7:$A$2006,"<"&$A23+1)) -> 0 | C23: =IF($A23="","",SUMIFS('Daily entries'!$D$7:$D$2006,'Daily entries'!$A$7:$A$2006,">="&$A23,'Daily entries'!$A$7:$A$2006,"<"&$A23+1)) -> 0 | D23: =IF(A23="","",B23-C23) -> 0 | E23: =IF(A23="","",FixedTotal/DAY(EOMONTH(MonthStart,0))) -> 987.64516 | F23: =IF(A23="","",D23-E23) -> -987.64516 | G23: =IF(A23="","",Overview!$C$6+SUM($F$7:F23)) -> -16789.968
A24: =IF(18<=DAY(EOMONTH(MonthStart,0)),MonthStart+17,"") -> 46313 | B24: =IF($A24="","",SUMIFS('Daily entries'!$C$7:$C$2006,'Daily entries'!$A$7:$A$2006,">="&$A24,'Daily entries'!$A$7:$A$2006,"<"&$A24+1)) -> 0 | C24: =IF($A24="","",SUMIFS('Daily entries'!$D$7:$D$2006,'Daily entries'!$A$7:$A$2006,">="&$A24,'Daily entries'!$A$7:$A$2006,"<"&$A24+1)) -> 0 | D24: =IF(A24="","",B24-C24) -> 0 | E24: =IF(A24="","",FixedTotal/DAY(EOMONTH(MonthStart,0))) -> 987.64516 | F24: =IF(A24="","",D24-E24) -> -987.64516 | G24: =IF(A24="","",Overview!$C$6+SUM($F$7:F24)) -> -17777.613
A25: =IF(19<=DAY(EOMONTH(MonthStart,0)),MonthStart+18,"") -> 46314 | B25: =IF($A25="","",SUMIFS('Daily entries'!$C$7:$C$2006,'Daily entries'!$A$7:$A$2006,">="&$A25,'Daily entries'!$A$7:$A$2006,"<"&$A25+1)) -> 0 | C25: =IF($A25="","",SUMIFS('Daily entries'!$D$7:$D$2006,'Daily entries'!$A$7:$A$2006,">="&$A25,'Daily entries'!$A$7:$A$2006,"<"&$A25+1)) -> 0 | D25: =IF(A25="","",B25-C25) -> 0 | E25: =IF(A25="","",FixedTotal/DAY(EOMONTH(MonthStart,0))) -> 987.64516 | F25: =IF(A25="","",D25-E25) -> -987.64516 | G25: =IF(A25="","",Overview!$C$6+SUM($F$7:F25)) -> -18765.258
A26: =IF(20<=DAY(EOMONTH(MonthStart,0)),MonthStart+19,"") -> 46315 | B26: =IF($A26="","",SUMIFS('Daily entries'!$C$7:$C$2006,'Daily entries'!$A$7:$A$2006,">="&$A26,'Daily entries'!$A$7:$A$2006,"<"&$A26+1)) -> 0 | C26: =IF($A26="","",SUMIFS('Daily entries'!$D$7:$D$2006,'Daily entries'!$A$7:$A$2006,">="&$A26,'Daily entries'!$A$7:$A$2006,"<"&$A26+1)) -> 0 | D26: =IF(A26="","",B26-C26) -> 0 | E26: =IF(A26="","",FixedTotal/DAY(EOMONTH(MonthStart,0))) -> 987.64516 | F26: =IF(A26="","",D26-E26) -> -987.64516 | G26: =IF(A26="","",Overview!$C$6+SUM($F$7:F26)) -> -19752.903
A27: =IF(21<=DAY(EOMONTH(MonthStart,0)),MonthStart+20,"") -> 46316 | B27: =IF($A27="","",SUMIFS('Daily entries'!$C$7:$C$2006,'Daily entries'!$A$7:$A$2006,">="&$A27,'Daily entries'!$A$7:$A$2006,"<"&$A27+1)) -> 0 | C27: =IF($A27="","",SUMIFS('Daily entries'!$D$7:$D$2006,'Daily entries'!$A$7:$A$2006,">="&$A27,'Daily entries'!$A$7:$A$2006,"<"&$A27+1)) -> 0 | D27: =IF(A27="","",B27-C27) -> 0 | E27: =IF(A27="","",FixedTotal/DAY(EOMONTH(MonthStart,0))) -> 987.64516 | F27: =IF(A27="","",D27-E27) -> -987.64516 | G27: =IF(A27="","",Overview!$C$6+SUM($F$7:F27)) -> -20740.548
A28: =IF(22<=DAY(EOMONTH(MonthStart,0)),MonthStart+21,"") -> 46317 | B28: =IF($A28="","",SUMIFS('Daily entries'!$C$7:$C$2006,'Daily entries'!$A$7:$A$2006,">="&$A28,'Daily entries'!$A$7:$A$2006,"<"&$A28+1)) -> 0 | C28: =IF($A28="","",SUMIFS('Daily entries'!$D$7:$D$2006,'Daily entries'!$A$7:$A$2006,">="&$A28,'Daily entries'!$A$7:$A$2006,"<"&$A28+1)) -> 0 | D28: =IF(A28="","",B28-C28) -> 0 | E28: =IF(A28="","",FixedTotal/DAY(EOMONTH(MonthStart,0))) -> 987.64516 | F28: =IF(A28="","",D28-E28) -> -987.64516 | G28: =IF(A28="","",Overview!$C$6+SUM($F$7:F28)) -> -21728.194
A29: =IF(23<=DAY(EOMONTH(MonthStart,0)),MonthStart+22,"") -> 46318 | B29: =IF($A29="","",SUMIFS('Daily entries'!$C$7:$C$2006,'Daily entries'!$A$7:$A$2006,">="&$A29,'Daily entries'!$A$7:$A$2006,"<"&$A29+1)) -> 0 | C29: =IF($A29="","",SUMIFS('Daily entries'!$D$7:$D$2006,'Daily entries'!$A$7:$A$2006,">="&$A29,'Daily entries'!$A$7:$A$2006,"<"&$A29+1)) -> 0 | D29: =IF(A29="","",B29-C29) -> 0 | E29: =IF(A29="","",FixedTotal/DAY(EOMONTH(MonthStart,0))) -> 987.64516 | F29: =IF(A29="","",D29-E29) -> -987.64516 | G29: =IF(A29="","",Overview!$C$6+SUM($F$7:F29)) -> -22715.839
A30: =IF(24<=DAY(EOMONTH(MonthStart,0)),MonthStart+23,"") -> 46319 | B30: =IF($A30="","",SUMIFS('Daily entries'!$C$7:$C$2006,'Daily entries'!$A$7:$A$2006,">="&$A30,'Daily entries'!$A$7:$A$2006,"<"&$A30+1)) -> 0 | C30: =IF($A30="","",SUMIFS('Daily entries'!$D$7:$D$2006,'Daily entries'!$A$7:$A$2006,">="&$A30,'Daily entries'!$A$7:$A$2006,"<"&$A30+1)) -> 0 | D30: =IF(A30="","",B30-C30) -> 0 | E30: =IF(A30="","",FixedTotal/DAY(EOMONTH(MonthStart,0))) -> 987.64516 | F30: =IF(A30="","",D30-E30) -> -987.64516 | G30: =IF(A30="","",Overview!$C$6+SUM($F$7:F30)) -> -23703.484
A31: =IF(25<=DAY(EOMONTH(MonthStart,0)),MonthStart+24,"") -> 46320 | B31: =IF($A31="","",SUMIFS('Daily entries'!$C$7:$C$2006,'Daily entries'!$A$7:$A$2006,">="&$A31,'Daily entries'!$A$7:$A$2006,"<"&$A31+1)) -> 0 | C31: =IF($A31="","",SUMIFS('Daily entries'!$D$7:$D$2006,'Daily entries'!$A$7:$A$2006,">="&$A31,'Daily entries'!$A$7:$A$2006,"<"&$A31+1)) -> 0 | D31: =IF(A31="","",B31-C31) -> 0 | E31: =IF(A31="","",FixedTotal/DAY(EOMONTH(MonthStart,0))) -> 987.64516 | F31: =IF(A31="","",D31-E31) -> -987.64516 | G31: =IF(A31="","",Overview!$C$6+SUM($F$7:F31)) -> -24691.129
A32: =IF(26<=DAY(EOMONTH(MonthStart,0)),MonthStart+25,"") -> 46321 | B32: =IF($A32="","",SUMIFS('Daily entries'!$C$7:$C$2006,'Daily entries'!$A$7:$A$2006,">="&$A32,'Daily entries'!$A$7:$A$2006,"<"&$A32+1)) -> 0 | C32: =IF($A32="","",SUMIFS('Daily entries'!$D$7:$D$2006,'Daily entries'!$A$7:$A$2006,">="&$A32,'Daily entries'!$A$7:$A$2006,"<"&$A32+1)) -> 0 | D32: =IF(A32="","",B32-C32) -> 0 | E32: =IF(A32="","",FixedTotal/DAY(EOMONTH(MonthStart,0))) -> 987.64516 | F32: =IF(A32="","",D32-E32) -> -987.64516 | G32: =IF(A32="","",Overview!$C$6+SUM($F$7:F32)) -> -25678.774
A33: =IF(27<=DAY(EOMONTH(MonthStart,0)),MonthStart+26,"") -> 46322 | B33: =IF($A33="","",SUMIFS('Daily entries'!$C$7:$C$2006,'Daily entries'!$A$7:$A$2006,">="&$A33,'Daily entries'!$A$7:$A$2006,"<"&$A33+1)) -> 0 | C33: =IF($A33="","",SUMIFS('Daily entries'!$D$7:$D$2006,'Daily entries'!$A$7:$A$2006,">="&$A33,'Daily entries'!$A$7:$A$2006,"<"&$A33+1)) -> 0 | D33: =IF(A33="","",B33-C33) -> 0 | E33: =IF(A33="","",FixedTotal/DAY(EOMONTH(MonthStart,0))) -> 987.64516 | F33: =IF(A33="","",D33-E33) -> -987.64516 | G33: =IF(A33="","",Overview!$C$6+SUM($F$7:F33)) -> -26666.419
A34: =IF(28<=DAY(EOMONTH(MonthStart,0)),MonthStart+27,"") -> 46323 | B34: =IF($A34="","",SUMIFS('Daily entries'!$C$7:$C$2006,'Daily entries'!$A$7:$A$2006,">="&$A34,'Daily entries'!$A$7:$A$2006,"<"&$A34+1)) -> 0 | C34: =IF($A34="","",SUMIFS('Daily entries'!$D$7:$D$2006,'Daily entries'!$A$7:$A$2006,">="&$A34,'Daily entries'!$A$7:$A$2006,"<"&$A34+1)) -> 0 | D34: =IF(A34="","",B34-C34) -> 0 | E34: =IF(A34="","",FixedTotal/DAY(EOMONTH(MonthStart,0))) -> 987.64516 | F34: =IF(A34="","",D34-E34) -> -987.64516 | G34: =IF(A34="","",Overview!$C$6+SUM($F$7:F34)) -> -27654.065
A35: =IF(29<=DAY(EOMONTH(MonthStart,0)),MonthStart+28,"") -> 46324 | B35: =IF($A35="","",SUMIFS('Daily entries'!$C$7:$C$2006,'Daily entries'!$A$7:$A$2006,">="&$A35,'Daily entries'!$A$7:$A$2006,"<"&$A35+1)) -> 0 | C35: =IF($A35="","",SUMIFS('Daily entries'!$D$7:$D$2006,'Daily entries'!$A$7:$A$2006,">="&$A35,'Daily entries'!$A$7:$A$2006,"<"&$A35+1)) -> 0 | D35: =IF(A35="","",B35-C35) -> 0 | E35: =IF(A35="","",FixedTotal/DAY(EOMONTH(MonthStart,0))) -> 987.64516 | F35: =IF(A35="","",D35-E35) -> -987.64516 | G35: =IF(A35="","",Overview!$C$6+SUM($F$7:F35)) -> -28641.71
A36: =IF(30<=DAY(EOMONTH(MonthStart,0)),MonthStart+29,"") -> 46325 | B36: =IF($A36="","",SUMIFS('Daily entries'!$C$7:$C$2006,'Daily entries'!$A$7:$A$2006,">="&$A36,'Daily entries'!$A$7:$A$2006,"<"&$A36+1)) -> 0 | C36: =IF($A36="","",SUMIFS('Daily entries'!$D$7:$D$2006,'Daily entries'!$A$7:$A$2006,">="&$A36,'Daily entries'!$A$7:$A$2006,"<"&$A36+1)) -> 0 | D36: =IF(A36="","",B36-C36) -> 0 | E36: =IF(A36="","",FixedTotal/DAY(EOMONTH(MonthStart,0))) -> 987.64516 | F36: =IF(A36="","",D36-E36) -> -987.64516 | G36: =IF(A36="","",Overview!$C$6+SUM($F$7:F36)) -> -29629.355
A37: =IF(31<=DAY(EOMONTH(MonthStart,0)),MonthStart+30,"") -> 46326 | B37: =IF($A37="","",SUMIFS('Daily entries'!$C$7:$C$2006,'Daily entries'!$A$7:$A$2006,">="&$A37,'Daily entries'!$A$7:$A$2006,"<"&$A37+1)) -> 0 | C37: =IF($A37="","",SUMIFS('Daily entries'!$D$7:$D$2006,'Daily entries'!$A$7:$A$2006,">="&$A37,'Daily entries'!$A$7:$A$2006,"<"&$A37+1)) -> 0 | D37: =IF(A37="","",B37-C37) -> 0 | E37: =IF(A37="","",FixedTotal/DAY(EOMONTH(MonthStart,0))) -> 987.64516 | F37: =IF(A37="","",D37-E37) -> -987.64516 | G37: =IF(A37="","",Overview!$C$6+SUM($F$7:F37)) -> -30617
A39: Monthly total | B39: =SUM(B7:B37) -> 0 | C39: =SUM(C7:C37) -> 0 | D39: =SUM(D7:D37) -> 0 | E39: =SUM(E7:E37) -> 30617 | F39: =SUM(F7:F37) -> -30617 | G39: =Overview!C6+SUM(F7:F37) -> -30617

Sheet Vodafone bills
A2: Vodafone — monthly bills
A3: Enter each month’s actual bill. Use a date in the month you want to budget it against. Blank means unknown. Enter 0 explicitly if no charge. Do not record it again elsewhere.
A6: Budget month / date | B6: Amount (CZK) | C6: Note
A7: 46296 | C7: Enter actual bill here; amount varies by month

Sheet Read me
B2: How to use your budget
B5: 1. Overview: choose the month and enter your opening balance for that month. The default is October 2026; replace it as needed.
B8: 2. Fixed costs: rent 19,500 Kč + internet 447 Kč + credit 10,670 Kč = 30,617 Kč per month. Monthly frequency is an assumption. For an annual bill, enter annual cost ÷ 12; for a weekly bill, use weekly cost × 52 ÷ 12.
B11: 3. Daily entries: enter actual dates, positive income or spending, and an optional category/note. Use one row per transaction or one row per day. There are 2,000 entry rows. Do not type into the calculated Entry net column.
B14: 4. Do not enter rent, internet, credit, Vodafone, or other fixed bills in Daily entries if they are already on Fixed costs. Otherwise your budget will subtract them twice.
B17: 5. Daily summary: income, everyday spending, cash flow, daily fixed reserve, and running budget are calculated automatically for the selected month. Negative figures mean a shortfall against the budget.
B20: 6. Remaining after fixed budget = opening balance + income − everyday spending − full monthly fixed budget. It does not represent a live bank balance or whether fixed bills have been paid.
B23: 7. Blue cells are editable. Formula cells calculate automatically in Excel. Changing fixed amounts updates all reviewed months; this workbook does not preserve a history of earlier fixed-cost rates.
B26: 8. Vodafone bills: enter the actual amount for each month separately. It is added to that month’s bills budget and daily reserve. An unknown bill is excluded and flagged on Overview. Never enter it twice. Money format is Czech koruna (CZK / Kč). English labels are used. No account numbers, passwords, macros, or external connections are included. Keep your personal finance file private.
B29: 9. Data entry tip: select dates using your normal Excel date format. A blank date with an amount is highlighted and excluded from the summaries until you add the date.
